hex_grid.py
hex_grid-0.7.1.dist-info/DESCRIPTION.rst
hex_grid-0.7.1.dist-info/METADATA
hex_grid-0.7.1.dist-info/RECORD
hex_grid-0.7.1.dist-info/WHEEL
hex_grid-0.7.1.dist-info/metadata.json
hex_grid-0.7.1.dist-info/top_level.txt
