Metadata-Version: 2.0
Name: hex-grid
Version: 0.7.1
Summary: hex grid utilities (for) Traveller/Cepheus System)
Home-page: https://github.com/makhidkarun/hex_grd
Author: Arthur Green
Author-email: arthur.green045@gmail.com
License: MIT
Platform: UNKNOWN
